{
  "url": "https://jekyllrb.com/",
  "requestedUrl": "https://jekyllrb.com/",
  "timestamp": 1602483344505,
  "ranks": {
    "hundos": 2,
    "performance": 3,
    "accessibility": 3,
    "cumulative": 2
  },
  "lighthouse": {
    "version": "6.4.1",
    "performance": 0.99,
    "accessibility": 1,
    "bestPractices": 1,
    "seo": 1,
    "total": 399
  },
  "firstContentfulPaint": 1058.2559999999999,
  "speedIndex": 1058.2559999999999,
  "largestContentfulPaint": 2129.0209999999997,
  "totalBlockingTime": 149,
  "cumulativeLayoutShift": 0,
  "timeToInteractive": 2279.0209999999997,
  "maxPotentialFirstInputDelay": 159,
  "timeToFirstByte": 13.351999999999999,
  "weight": {
    "summary": "10 requests • 195 KiB",
    "total": 199964,
    "image": 72680,
    "imageCount": 3,
    "script": 63412,
    "scriptCount": 2,
    "document": 3625,
    "font": 46406,
    "fontCount": 2,
    "stylesheet": 13777,
    "stylesheetCount": 1,
    "thirdParty": 63476,
    "thirdPartyCount": 3
  },
  "axe": {
    "passes": 249,
    "violations": 6
  }
}